test
archives_org_latin_toolkit
