Metadata-Version: 1.0
Name: archives-org-latin-toolkit
Version: 0.0.2
Summary: Tools to parse and search across http://www.cs.cmu.edu/~dbamman/latin.html
Home-page: http://github.com/ponteineptique/archives_org_latin
Author: Thibault Clérice
Author-email: leponteineptique@gmail.com
License: MIT
Platform: UNKNOWN
